{
  "agents": {
    "bi-finance": {
      "lastRun": null,
      "consecutiveErrors": 8,
      "nextAllowedRun": "2026-02-18T13:56:25.505Z"
    },
    "ceo": {
      "lastRun": null,
      "consecutiveErrors": 9,
      "nextAllowedRun": "2026-02-18T14:22:46.089Z"
    },
    "marketing": {
      "lastRun": null,
      "consecutiveErrors": 8,
      "nextAllowedRun": "2026-02-18T13:56:01.350Z"
    },
    "operations": {
      "lastRun": null,
      "consecutiveErrors": 8,
      "nextAllowedRun": "2026-02-18T13:54:28.719Z"
    },
    "technology": {
      "lastRun": null,
      "consecutiveErrors": 8,
      "nextAllowedRun": "2026-02-18T13:53:44.149Z"
    }
  },
  "lastReleasesCheck": "2026-02-18T13:16:02.404Z",
  "lastArchiveCleanup": "2026-02-18T13:16:02.407Z"
}