{
  "agents": {
    "bi-finance": {
      "lastRun": null,
      "consecutiveErrors": 11,
      "nextAllowedRun": "2026-02-18T15:28:16.291Z"
    },
    "ceo": {
      "lastRun": null,
      "consecutiveErrors": 12,
      "nextAllowedRun": "2026-02-18T15:54:17.988Z"
    },
    "marketing": {
      "lastRun": null,
      "consecutiveErrors": 11,
      "nextAllowedRun": "2026-02-18T15:27:32.250Z"
    },
    "operations": {
      "lastRun": null,
      "consecutiveErrors": 12,
      "nextAllowedRun": "2026-02-18T15:56:17.107Z"
    },
    "technology": {
      "lastRun": null,
      "consecutiveErrors": 12,
      "nextAllowedRun": "2026-02-18T15:55:38.019Z"
    }
  },
  "lastReleasesCheck": "2026-02-18T15:16:04.015Z",
  "lastArchiveCleanup": "2026-02-18T15:16:04.017Z"
}